lektor_open_graph.py
Lektor_Open_Graph-1b4.dist-info/LICENSE.txt
Lektor_Open_Graph-1b4.dist-info/METADATA
Lektor_Open_Graph-1b4.dist-info/RECORD
Lektor_Open_Graph-1b4.dist-info/WHEEL
Lektor_Open_Graph-1b4.dist-info/entry_points.txt
Lektor_Open_Graph-1b4.dist-info/top_level.txt
