Metadata-Version: 2.1
Name: Lektor-Open-Graph
Version: 1b4
Summary: Add Open Graph tags to Lektor pages.
Home-page: https://github.com/davidism/lektor-open-graph/
Author: David Lord
Author-email: davidism@gmail.com
License: BSD
Platform: UNKNOWN
Classifier: Development Status :: 4 - Beta
Classifier: License :: OSI Approved :: BSD License
Classifier: Programming Language :: Python
Classifier: Topic :: Internet :: WWW/HTTP :: Dynamic Content
